[
  {
    "id": 6070,
    "date": 20170811,
    "stockId": 256,
    "flag1": false,
    "price": 2.26,
    "change": -0.04,
    "changePercent": -1.74,
    "high": 2.31,
    "low": 2.21,
    "volume": 356006.0,
    "marketCapital": 808805.0,
    "oneYearChange": null
  },
  {
    "id": 6071,
    "date": 20170810,
    "stockId": 256,
    "flag1": false,
    "price": 2.30,
    "change": 0.00,
    "changePercent": 0.00,
    "high": 2.33,
    "low": 2.28,
    "volume": 126817.0,
    "marketCapital": 293046.0,
    "oneYearChange": null
  },
  {
    "id": 6072,
    "date": 20170809,
    "stockId": 256,
    "flag1": false,
    "price": 2.30,
    "change": -0.04,
    "changePercent": -1.71,
    "high": 2.38,
    "low": 2.29,
    "volume": 110663.0,
    "marketCapital": 256747.0,
    "oneYearChange": null
  },
  {
    "id": 6073,
    "date": 20170808,
    "stockId": 256,
    "flag1": false,
    "price": 2.34,
    "change": -0.02,
    "changePercent": -0.85,
    "high": 2.39,
    "low": 2.34,
    "volume": 121949.0,
    "marketCapital": 286776.0,
    "oneYearChange": null
  },
  {
    "id": 6074,
    "date": 20170807,
    "stockId": 256,
    "flag1": false,
    "price": 2.36,
    "change": 0.03,
    "changePercent": 1.29,
    "high": 2.39,
    "low": 2.33,
    "volume": 77013.0,
    "marketCapital": 182995.0,
    "oneYearChange": null
  },
  {
    "id": 6075,
    "date": 20170804,
    "stockId": 256,
    "flag1": false,
    "price": 2.33,
    "change": 0.03,
    "changePercent": 1.30,
    "high": 2.36,
    "low": 2.30,
    "volume": 124852.0,
    "marketCapital": 291449.0,
    "oneYearChange": null
  },
  {
    "id": 6076,
    "date": 20170803,
    "stockId": 256,
    "flag1": false,
    "price": 2.30,
    "change": -0.03,
    "changePercent": -1.29,
    "high": 2.34,
    "low": 2.30,
    "volume": 81710.0,
    "marketCapital": 189550.0,
    "oneYearChange": null
  },
  {
    "id": 6077,
    "date": 20170802,
    "stockId": 256,
    "flag1": false,
    "price": 2.33,
    "change": 0.02,
    "changePercent": 0.87,
    "high": 2.33,
    "low": 2.31,
    "volume": 60147.0,
    "marketCapital": 139947.0,
    "oneYearChange": null
  },
  {
    "id": 6078,
    "date": 20170801,
    "stockId": 256,
    "flag1": false,
    "price": 2.31,
    "change": -0.01,
    "changePercent": -0.43,
    "high": 2.33,
    "low": 2.29,
    "volume": 368237.0,
    "marketCapital": 852165.0,
    "oneYearChange": null
  },
  {
    "id": 6079,
    "date": 20170731,
    "stockId": 256,
    "flag1": false,
    "price": 2.32,
    "change": 0.04,
    "changePercent": 1.75,
    "high": 2.33,
    "low": 2.29,
    "volume": 43238.0,
    "marketCapital": 100447.0,
    "oneYearChange": null
  },
  {
    "id": 6080,
    "date": 20170728,
    "stockId": 256,
    "flag1": false,
    "price": 2.28,
    "change": -0.04,
    "changePercent": -1.72,
    "high": 2.32,
    "low": 2.28,
    "volume": 61348.0,
    "marketCapital": 140899.0,
    "oneYearChange": null
  },
  {
    "id": 6081,
    "date": 20170727,
    "stockId": 256,
    "flag1": false,
    "price": 2.32,
    "change": -0.03,
    "changePercent": -1.28,
    "high": 2.35,
    "low": 2.28,
    "volume": 273272.0,
    "marketCapital": 635232.0,
    "oneYearChange": null
  },
  {
    "id": 6082,
    "date": 20170726,
    "stockId": 256,
    "flag1": false,
    "price": 2.35,
    "change": -0.02,
    "changePercent": -0.84,
    "high": 2.38,
    "low": 2.35,
    "volume": 161246.0,
    "marketCapital": 382452.0,
    "oneYearChange": null
  },
  {
    "id": 6083,
    "date": 20170725,
    "stockId": 256,
    "flag1": false,
    "price": 2.37,
    "change": 0.04,
    "changePercent": 1.72,
    "high": 2.375,
    "low": 2.31,
    "volume": 201184.0,
    "marketCapital": 471733.0,
    "oneYearChange": null
  },
  {
    "id": 6084,
    "date": 20170724,
    "stockId": 256,
    "flag1": false,
    "price": 2.33,
    "change": 0.04,
    "changePercent": 1.75,
    "high": 2.35,
    "low": 2.29,
    "volume": 92763.0,
    "marketCapital": 215325.0,
    "oneYearChange": null
  },
  {
    "id": 6085,
    "date": 20170721,
    "stockId": 256,
    "flag1": false,
    "price": 2.29,
    "change": 0.05,
    "changePercent": 2.23,
    "high": 2.31,
    "low": 2.24,
    "volume": 148259.0,
    "marketCapital": 339219.0,
    "oneYearChange": null
  },
  {
    "id": 6086,
    "date": 20170720,
    "stockId": 256,
    "flag1": false,
    "price": 2.24,
    "change": 0.01,
    "changePercent": 0.45,
    "high": 2.27,
    "low": 2.24,
    "volume": 103757.0,
    "marketCapital": 234482.0,
    "oneYearChange": null
  },
  {
    "id": 6087,
    "date": 20170719,
    "stockId": 256,
    "flag1": false,
    "price": 2.23,
    "change": 0.00,
    "changePercent": 0.00,
    "high": 2.27,
    "low": 2.23,
    "volume": 142199.0,
    "marketCapital": 320443.0,
    "oneYearChange": null
  },
  {
    "id": 6088,
    "date": 20170718,
    "stockId": 256,
    "flag1": false,
    "price": 2.23,
    "change": -0.01,
    "changePercent": -0.45,
    "high": 2.25,
    "low": 2.21,
    "volume": 132133.0,
    "marketCapital": 293897.0,
    "oneYearChange": null
  },
  {
    "id": 6089,
    "date": 20170717,
    "stockId": 256,
    "flag1": false,
    "price": 2.24,
    "change": 0.03,
    "changePercent": 1.36,
    "high": 2.25,
    "low": 2.22,
    "volume": 52781.0,
    "marketCapital": 117853.0,
    "oneYearChange": null
  }
]