[
  {
    "id": 495,
    "date": 20170815,
    "stockId": 1,
    "flag1": false,
    "price": 5.07,
    "change": 0.01,
    "changePercent": 0.20,
    "high": 5.115,
    "low": 5.04,
    "volume": 10123374.0,
    "marketCapital": 14796638525.0,
    "oneYearChange": -12.89
  },
  {
    "id": 497,
    "date": 20170815,
    "stockId": 2,
    "flag1": false,
    "price": 29.81,
    "change": 0.38,
    "changePercent": 1.29,
    "high": 29.97,
    "low": 29.70,
    "volume": 4930268.0,
    "marketCapital": 87564350898.0,
    "oneYearChange": 12.03
  },
  {
    "id": 498,
    "date": 20170815,
    "stockId": 3,
    "flag1": false,
    "price": 25.61,
    "change": -0.04,
    "changePercent": -0.16,
    "high": 25.87,
    "low": 25.54,
    "volume": 4958017.0,
    "marketCapital": 82251409199.0,
    "oneYearChange": 27.03
  },
  {
    "id": 499,
    "date": 20170815,
    "stockId": 4,
    "flag1": false,
    "price": 9.73,
    "change": 0.01,
    "changePercent": 0.10,
    "high": 9.77,
    "low": 9.70,
    "volume": 2117520.0,
    "marketCapital": 15465514640.0,
    "oneYearChange": -27.17
  },
  {
    "id": 500,
    "date": 20170815,
    "stockId": 5,
    "flag1": false,
    "price": 81.25,
    "change": -0.06,
    "changePercent": -0.07,
    "high": 81.95,
    "low": 81.14,
    "volume": 2846024.0,
    "marketCapital": 140551788081.0,
    "oneYearChange": 6.49
  },
  {
    "id": 501,
    "date": 20170815,
    "stockId": 6,
    "flag1": false,
    "price": 127.18,
    "change": 0.87,
    "changePercent": 0.69,
    "high": 128.84,
    "low": 127.09,
    "volume": 495570.0,
    "marketCapital": 57546481945.0,
    "oneYearChange": 9.37
  },
  {
    "id": 502,
    "date": 20170815,
    "stockId": 7,
    "flag1": false,
    "price": 6.66,
    "change": 0.02,
    "changePercent": 0.30,
    "high": 6.685,
    "low": 6.62,
    "volume": 9704509.0,
    "marketCapital": 15767712131.0,
    "oneYearChange": 8.29
  },
  {
    "id": 503,
    "date": 20170815,
    "stockId": 8,
    "flag1": false,
    "price": 87.76,
    "change": 0.41,
    "changePercent": 0.47,
    "high": 88.24,
    "low": 87.48,
    "volume": 682720.0,
    "marketCapital": 29869809567.0,
    "oneYearChange": 12.31
  },
  {
    "id": 504,
    "date": 20170815,
    "stockId": 9,
    "flag1": false,
    "price": 30.89,
    "change": 0.18,
    "changePercent": 0.59,
    "high": 31.09,
    "low": 30.795,
    "volume": 2914862.0,
    "marketCapital": 82954086967.0,
    "oneYearChange": 13.57
  },
  {
    "id": 505,
    "date": 20170815,
    "stockId": 10,
    "flag1": false,
    "price": 11.80,
    "change": 0.10,
    "changePercent": 0.86,
    "high": 11.885,
    "low": 11.755,
    "volume": 4458585.0,
    "marketCapital": 16189982591.0,
    "oneYearChange": 4.70
  },
  {
    "id": 506,
    "date": 20170815,
    "stockId": 11,
    "flag1": true,
    "price": 62.82,
    "change": -0.60,
    "changePercent": -0.95,
    "high": 63.80,
    "low": 62.66,
    "volume": 2116396.0,
    "marketCapital": 26647767322.0,
    "oneYearChange": 30.77
  },
  {
    "id": 507,
    "date": 20170815,
    "stockId": 12,
    "flag1": false,
    "price": 4.00,
    "change": 0.03,
    "changePercent": 0.76,
    "high": 4.065,
    "low": 4.00,
    "volume": 13352013.0,
    "marketCapital": 21297186712.0,
    "oneYearChange": -20.79
  },
  {
    "id": 508,
    "date": 20170815,
    "stockId": 13,
    "flag1": false,
    "price": 13.56,
    "change": 0.10,
    "changePercent": 0.74,
    "high": 13.58,
    "low": 13.46,
    "volume": 4110444.0,
    "marketCapital": 17529010481.0,
    "oneYearChange": 2.65
  },
  {
    "id": 509,
    "date": 20170815,
    "stockId": 14,
    "flag1": false,
    "price": 11.70,
    "change": 0.09,
    "changePercent": 0.78,
    "high": 11.76,
    "low": 11.65,
    "volume": 2419428.0,
    "marketCapital": 24032922170.0,
    "oneYearChange": -1.93
  },
  {
    "id": 510,
    "date": 20170815,
    "stockId": 15,
    "flag1": false,
    "price": 4.24,
    "change": 0.07,
    "changePercent": 1.68,
    "high": 4.24,
    "low": 4.19,
    "volume": 32570251.0,
    "marketCapital": 50427582905.0,
    "oneYearChange": -22.77
  },
  {
    "id": 511,
    "date": 20170815,
    "stockId": 16,
    "flag1": false,
    "price": 32.19,
    "change": 0.21,
    "changePercent": 0.66,
    "high": 32.41,
    "low": 32.17,
    "volume": 2921685.0,
    "marketCapital": 109264586141.0,
    "oneYearChange": 8.17
  },
  {
    "id": 512,
    "date": 20170815,
    "stockId": 17,
    "flag1": false,
    "price": 41.57,
    "change": 0.45,
    "changePercent": 1.09,
    "high": 41.59,
    "low": 41.24,
    "volume": 1792428.0,
    "marketCapital": 47133738860.0,
    "oneYearChange": -2.42
  },
  {
    "id": 513,
    "date": 20170815,
    "stockId": 18,
    "flag1": false,
    "price": 7.58,
    "change": 0.05,
    "changePercent": 0.66,
    "high": 7.67,
    "low": 7.57,
    "volume": 5058878.0,
    "marketCapital": 15751919820.0,
    "oneYearChange": -27.95
  },
  {
    "id": 514,
    "date": 20170815,
    "stockId": 19,
    "flag1": false,
    "price": 27.09,
    "change": 0.19,
    "changePercent": 0.71,
    "high": 27.115,
    "low": 26.97,
    "volume": 2238650.0,
    "marketCapital": 35065742443.0,
    "oneYearChange": 15.33
  },
  {
    "id": 515,
    "date": 20170815,
    "stockId": 20,
    "flag1": false,
    "price": 29.14,
    "change": -0.09,
    "changePercent": -0.31,
    "high": 29.23,
    "low": 29.01,
    "volume": 1486680.0,
    "marketCapital": 24548844473.0,
    "oneYearChange": 6.39
  }
]