[
  {
    "id": 9373,
    "date": 20170811,
    "stockId": 422,
    "flag1": false,
    "price": 0.55,
    "change": 0.01,
    "changePercent": 1.85,
    "high": 0.57,
    "low": 0.55,
    "volume": 168756.0,
    "marketCapital": 94245.0,
    "oneYearChange": null
  },
  {
    "id": 9374,
    "date": 20170810,
    "stockId": 422,
    "flag1": false,
    "price": 0.54,
    "change": -0.04,
    "changePercent": -6.90,
    "high": 0.63,
    "low": 0.54,
    "volume": 1223938.0,
    "marketCapital": 702735.0,
    "oneYearChange": null
  },
  {
    "id": 9375,
    "date": 20170809,
    "stockId": 422,
    "flag1": false,
    "price": 0.58,
    "change": -0.01,
    "changePercent": -1.69,
    "high": 0.58,
    "low": 0.565,
    "volume": 355701.0,
    "marketCapital": 203420.0,
    "oneYearChange": null
  },
  {
    "id": 9376,
    "date": 20170808,
    "stockId": 422,
    "flag1": false,
    "price": 0.59,
    "change": 0.005,
    "changePercent": 0.85,
    "high": 0.59,
    "low": 0.57,
    "volume": 352781.0,
    "marketCapital": 203559.0,
    "oneYearChange": null
  },
  {
    "id": 9377,
    "date": 20170807,
    "stockId": 422,
    "flag1": false,
    "price": 0.585,
    "change": 0.025,
    "changePercent": 4.46,
    "high": 0.595,
    "low": 0.565,
    "volume": 568363.0,
    "marketCapital": 331526.0,
    "oneYearChange": null
  },
  {
    "id": 9378,
    "date": 20170804,
    "stockId": 422,
    "flag1": false,
    "price": 0.56,
    "change": 0.00,
    "changePercent": 0.00,
    "high": 0.575,
    "low": 0.56,
    "volume": 312647.0,
    "marketCapital": 176080.0,
    "oneYearChange": null
  },
  {
    "id": 9379,
    "date": 20170803,
    "stockId": 422,
    "flag1": false,
    "price": 0.56,
    "change": -0.015,
    "changePercent": -2.61,
    "high": 0.595,
    "low": 0.555,
    "volume": 785260.0,
    "marketCapital": 447077.0,
    "oneYearChange": null
  },
  {
    "id": 9380,
    "date": 20170802,
    "stockId": 422,
    "flag1": false,
    "price": 0.575,
    "change": -0.025,
    "changePercent": -4.17,
    "high": 0.60,
    "low": 0.57,
    "volume": 896142.0,
    "marketCapital": 520940.0,
    "oneYearChange": null
  },
  {
    "id": 9381,
    "date": 20170801,
    "stockId": 422,
    "flag1": false,
    "price": 0.60,
    "change": -0.04,
    "changePercent": -6.25,
    "high": 0.635,
    "low": 0.585,
    "volume": 2304622.0,
    "marketCapital": 1400440.0,
    "oneYearChange": null
  },
  {
    "id": 9382,
    "date": 20170731,
    "stockId": 422,
    "flag1": false,
    "price": 0.64,
    "change": -0.02,
    "changePercent": -3.03,
    "high": 0.68,
    "low": 0.64,
    "volume": 1901658.0,
    "marketCapital": 1247154.0,
    "oneYearChange": null
  },
  {
    "id": 9383,
    "date": 20170728,
    "stockId": 422,
    "flag1": false,
    "price": 0.66,
    "change": 0.015,
    "changePercent": 2.33,
    "high": 0.67,
    "low": 0.635,
    "volume": 1786011.0,
    "marketCapital": 1164105.0,
    "oneYearChange": null
  },
  {
    "id": 9384,
    "date": 20170727,
    "stockId": 422,
    "flag1": false,
    "price": 0.645,
    "change": 0.02,
    "changePercent": 3.20,
    "high": 0.655,
    "low": 0.635,
    "volume": 2515109.0,
    "marketCapital": 1632242.0,
    "oneYearChange": null
  },
  {
    "id": 9385,
    "date": 20170726,
    "stockId": 422,
    "flag1": false,
    "price": 0.625,
    "change": 0.075,
    "changePercent": 13.64,
    "high": 0.68,
    "low": 0.605,
    "volume": 7065147.0,
    "marketCapital": 4514474.0,
    "oneYearChange": null
  },
  {
    "id": 9386,
    "date": 20170725,
    "stockId": 422,
    "flag1": false,
    "price": 0.55,
    "change": -0.45,
    "changePercent": -45.00,
    "high": 0.61,
    "low": 0.54,
    "volume": 19129134.0,
    "marketCapital": 11012406.0,
    "oneYearChange": null
  },
  {
    "id": 9387,
    "date": 20170724,
    "stockId": 422,
    "flag1": false,
    "price": 1.00,
    "change": 0.01,
    "changePercent": 1.01,
    "high": 1.00,
    "low": 0.99,
    "volume": 360324.0,
    "marketCapital": 358666.0,
    "oneYearChange": null
  },
  {
    "id": 9388,
    "date": 20170721,
    "stockId": 422,
    "flag1": false,
    "price": 0.99,
    "change": 0.005,
    "changePercent": 0.51,
    "high": 0.99,
    "low": 0.98,
    "volume": 264067.0,
    "marketCapital": 260246.0,
    "oneYearChange": null
  },
  {
    "id": 9389,
    "date": 20170720,
    "stockId": 422,
    "flag1": false,
    "price": 0.985,
    "change": -0.01,
    "changePercent": -1.01,
    "high": 0.99,
    "low": 0.98,
    "volume": 101905.0,
    "marketCapital": 100605.0,
    "oneYearChange": null
  },
  {
    "id": 9390,
    "date": 20170719,
    "stockId": 422,
    "flag1": false,
    "price": 0.995,
    "change": 0.00,
    "changePercent": 0.00,
    "high": 1.00,
    "low": 0.985,
    "volume": 130669.0,
    "marketCapital": 129599.0,
    "oneYearChange": null
  },
  {
    "id": 9391,
    "date": 20170718,
    "stockId": 422,
    "flag1": false,
    "price": 0.995,
    "change": -0.035,
    "changePercent": -3.40,
    "high": 1.02,
    "low": 0.995,
    "volume": 101252.0,
    "marketCapital": 102134.0,
    "oneYearChange": null
  },
  {
    "id": 9392,
    "date": 20170717,
    "stockId": 422,
    "flag1": false,
    "price": 1.03,
    "change": 0.00,
    "changePercent": 0.00,
    "high": 1.075,
    "low": 1.02,
    "volume": 378409.0,
    "marketCapital": 394261.0,
    "oneYearChange": null
  }
]