[
  {
    "id": 3787,
    "date": 20170811,
    "stockId": 141,
    "flag1": false,
    "price": 2.65,
    "change": 0.00,
    "changePercent": 0.00,
    "high": 2.66,
    "low": 2.61,
    "volume": 680820.0,
    "marketCapital": 1801402.0,
    "oneYearChange": null
  },
  {
    "id": 3788,
    "date": 20170810,
    "stockId": 141,
    "flag1": false,
    "price": 2.65,
    "change": 0.04,
    "changePercent": 1.53,
    "high": 2.66,
    "low": 2.61,
    "volume": 1176761.0,
    "marketCapital": 3115720.0,
    "oneYearChange": null
  },
  {
    "id": 3789,
    "date": 20170809,
    "stockId": 141,
    "flag1": false,
    "price": 2.61,
    "change": -0.01,
    "changePercent": -0.38,
    "high": 2.64,
    "low": 2.59,
    "volume": 348747.0,
    "marketCapital": 913604.0,
    "oneYearChange": null
  },
  {
    "id": 3790,
    "date": 20170808,
    "stockId": 141,
    "flag1": false,
    "price": 2.62,
    "change": -0.08,
    "changePercent": -2.96,
    "high": 2.71,
    "low": 2.59,
    "volume": 396755.0,
    "marketCapital": 1036861.0,
    "oneYearChange": null
  },
  {
    "id": 3791,
    "date": 20170807,
    "stockId": 141,
    "flag1": false,
    "price": 2.70,
    "change": 0.06,
    "changePercent": 2.27,
    "high": 2.72,
    "low": 2.67,
    "volume": 367310.0,
    "marketCapital": 987785.0,
    "oneYearChange": null
  },
  {
    "id": 3792,
    "date": 20170804,
    "stockId": 141,
    "flag1": false,
    "price": 2.64,
    "change": 0.00,
    "changePercent": 0.00,
    "high": 2.64,
    "low": 2.59,
    "volume": 303693.0,
    "marketCapital": 798075.0,
    "oneYearChange": null
  },
  {
    "id": 3793,
    "date": 20170803,
    "stockId": 141,
    "flag1": false,
    "price": 2.64,
    "change": -0.01,
    "changePercent": -0.38,
    "high": 2.66,
    "low": 2.59,
    "volume": 343763.0,
    "marketCapital": 904122.0,
    "oneYearChange": null
  },
  {
    "id": 3794,
    "date": 20170802,
    "stockId": 141,
    "flag1": false,
    "price": 2.65,
    "change": 0.05,
    "changePercent": 1.92,
    "high": 2.69,
    "low": 2.62,
    "volume": 470030.0,
    "marketCapital": 1250073.0,
    "oneYearChange": null
  },
  {
    "id": 3795,
    "date": 20170801,
    "stockId": 141,
    "flag1": false,
    "price": 2.60,
    "change": 0.00,
    "changePercent": 0.00,
    "high": 2.62,
    "low": 2.58,
    "volume": 318198.0,
    "marketCapital": 827591.0,
    "oneYearChange": null
  },
  {
    "id": 3796,
    "date": 20170731,
    "stockId": 141,
    "flag1": false,
    "price": 2.60,
    "change": 0.04,
    "changePercent": 1.56,
    "high": 2.63,
    "low": 2.55,
    "volume": 231041.0,
    "marketCapital": 599797.0,
    "oneYearChange": null
  },
  {
    "id": 3797,
    "date": 20170728,
    "stockId": 141,
    "flag1": false,
    "price": 2.56,
    "change": -0.08,
    "changePercent": -3.03,
    "high": 2.65,
    "low": 2.56,
    "volume": 524745.0,
    "marketCapital": 1354892.0,
    "oneYearChange": null
  },
  {
    "id": 3798,
    "date": 20170727,
    "stockId": 141,
    "flag1": false,
    "price": 2.64,
    "change": 0.07,
    "changePercent": 2.72,
    "high": 2.65,
    "low": 2.555,
    "volume": 418454.0,
    "marketCapital": 1095424.0,
    "oneYearChange": null
  },
  {
    "id": 3799,
    "date": 20170726,
    "stockId": 141,
    "flag1": false,
    "price": 2.57,
    "change": 0.06,
    "changePercent": 2.39,
    "high": 2.57,
    "low": 2.505,
    "volume": 3091205.0,
    "marketCapital": 7832502.0,
    "oneYearChange": null
  },
  {
    "id": 3800,
    "date": 20170725,
    "stockId": 141,
    "flag1": false,
    "price": 2.51,
    "change": 0.00,
    "changePercent": 0.00,
    "high": 2.53,
    "low": 2.49,
    "volume": 136820.0,
    "marketCapital": 343269.0,
    "oneYearChange": null
  },
  {
    "id": 3801,
    "date": 20170724,
    "stockId": 141,
    "flag1": false,
    "price": 2.51,
    "change": -0.01,
    "changePercent": -0.40,
    "high": 2.53,
    "low": 2.48,
    "volume": 810663.0,
    "marketCapital": 2029258.0,
    "oneYearChange": null
  },
  {
    "id": 3802,
    "date": 20170721,
    "stockId": 141,
    "flag1": false,
    "price": 2.52,
    "change": -0.02,
    "changePercent": -0.79,
    "high": 2.54,
    "low": 2.49,
    "volume": 637030.0,
    "marketCapital": 1606734.0,
    "oneYearChange": null
  },
  {
    "id": 3803,
    "date": 20170720,
    "stockId": 141,
    "flag1": false,
    "price": 2.54,
    "change": 0.01,
    "changePercent": 0.40,
    "high": 2.57,
    "low": 2.53,
    "volume": 401776.0,
    "marketCapital": 1023631.0,
    "oneYearChange": null
  },
  {
    "id": 3804,
    "date": 20170719,
    "stockId": 141,
    "flag1": false,
    "price": 2.53,
    "change": 0.03,
    "changePercent": 1.20,
    "high": 2.55,
    "low": 2.48,
    "volume": 753433.0,
    "marketCapital": 1904570.0,
    "oneYearChange": null
  },
  {
    "id": 3805,
    "date": 20170718,
    "stockId": 141,
    "flag1": false,
    "price": 2.50,
    "change": -0.04,
    "changePercent": -1.57,
    "high": 2.54,
    "low": 2.48,
    "volume": 504177.0,
    "marketCapital": 1258792.0,
    "oneYearChange": null
  },
  {
    "id": 3806,
    "date": 20170717,
    "stockId": 141,
    "flag1": false,
    "price": 2.54,
    "change": 0.01,
    "changePercent": 0.40,
    "high": 2.545,
    "low": 2.52,
    "volume": 233419.0,
    "marketCapital": 591839.0,
    "oneYearChange": null
  }
]