[
  {
    "id": 5470,
    "date": 20170811,
    "stockId": 226,
    "flag1": false,
    "price": 0.245,
    "change": 0.005,
    "changePercent": 2.08,
    "high": 0.25,
    "low": 0.235,
    "volume": 2171577.0,
    "marketCapital": 530400.0,
    "oneYearChange": null
  },
  {
    "id": 5471,
    "date": 20170810,
    "stockId": 226,
    "flag1": false,
    "price": 0.24,
    "change": 0.00,
    "changePercent": 0.00,
    "high": 0.25,
    "low": 0.24,
    "volume": 957217.0,
    "marketCapital": 233863.0,
    "oneYearChange": null
  },
  {
    "id": 5472,
    "date": 20170809,
    "stockId": 226,
    "flag1": false,
    "price": 0.24,
    "change": 0.01,
    "changePercent": 4.35,
    "high": 0.25,
    "low": 0.225,
    "volume": 2175517.0,
    "marketCapital": 518716.0,
    "oneYearChange": null
  },
  {
    "id": 5473,
    "date": 20170808,
    "stockId": 226,
    "flag1": false,
    "price": 0.23,
    "change": 0.00,
    "changePercent": 0.00,
    "high": 0.235,
    "low": 0.225,
    "volume": 871267.0,
    "marketCapital": 200602.0,
    "oneYearChange": null
  },
  {
    "id": 5474,
    "date": 20170807,
    "stockId": 226,
    "flag1": false,
    "price": 0.23,
    "change": 0.005,
    "changePercent": 2.22,
    "high": 0.25,
    "low": 0.23,
    "volume": 3124919.0,
    "marketCapital": 747723.0,
    "oneYearChange": null
  },
  {
    "id": 5475,
    "date": 20170804,
    "stockId": 226,
    "flag1": false,
    "price": 0.225,
    "change": -0.015,
    "changePercent": -6.25,
    "high": 0.25,
    "low": 0.22,
    "volume": 2839319.0,
    "marketCapital": 671405.0,
    "oneYearChange": null
  },
  {
    "id": 5476,
    "date": 20170803,
    "stockId": 226,
    "flag1": false,
    "price": 0.24,
    "change": 0.01,
    "changePercent": 4.35,
    "high": 0.25,
    "low": 0.235,
    "volume": 2852367.0,
    "marketCapital": 690782.0,
    "oneYearChange": null
  },
  {
    "id": 5477,
    "date": 20170802,
    "stockId": 226,
    "flag1": false,
    "price": 0.23,
    "change": 0.02,
    "changePercent": 9.52,
    "high": 0.23,
    "low": 0.215,
    "volume": 2374889.0,
    "marketCapital": 528369.0,
    "oneYearChange": null
  },
  {
    "id": 5478,
    "date": 20170801,
    "stockId": 226,
    "flag1": false,
    "price": 0.21,
    "change": 0.015,
    "changePercent": 7.69,
    "high": 0.215,
    "low": 0.20,
    "volume": 4384612.0,
    "marketCapital": 919919.0,
    "oneYearChange": null
  },
  {
    "id": 5479,
    "date": 20170731,
    "stockId": 226,
    "flag1": false,
    "price": 0.195,
    "change": 0.00,
    "changePercent": 0.00,
    "high": 0.20,
    "low": 0.19,
    "volume": 557661.0,
    "marketCapital": 109235.0,
    "oneYearChange": null
  },
  {
    "id": 5480,
    "date": 20170728,
    "stockId": 226,
    "flag1": false,
    "price": 0.195,
    "change": -0.005,
    "changePercent": -2.50,
    "high": 0.20,
    "low": 0.19,
    "volume": 891102.0,
    "marketCapital": 173728.0,
    "oneYearChange": null
  },
  {
    "id": 5481,
    "date": 20170727,
    "stockId": 226,
    "flag1": false,
    "price": 0.20,
    "change": 0.01,
    "changePercent": 5.26,
    "high": 0.205,
    "low": 0.195,
    "volume": 900292.0,
    "marketCapital": 179554.0,
    "oneYearChange": null
  },
  {
    "id": 5482,
    "date": 20170726,
    "stockId": 226,
    "flag1": false,
    "price": 0.19,
    "change": 0.00,
    "changePercent": 0.00,
    "high": 0.20,
    "low": 0.19,
    "volume": 669480.0,
    "marketCapital": 130136.0,
    "oneYearChange": null
  },
  {
    "id": 5483,
    "date": 20170725,
    "stockId": 226,
    "flag1": false,
    "price": 0.19,
    "change": -0.01,
    "changePercent": -5.00,
    "high": 0.20,
    "low": 0.19,
    "volume": 871889.0,
    "marketCapital": 169890.0,
    "oneYearChange": null
  },
  {
    "id": 5484,
    "date": 20170724,
    "stockId": 226,
    "flag1": false,
    "price": 0.20,
    "change": -0.01,
    "changePercent": -4.76,
    "high": 0.21,
    "low": 0.19,
    "volume": 1751401.0,
    "marketCapital": 353677.0,
    "oneYearChange": null
  },
  {
    "id": 5485,
    "date": 20170721,
    "stockId": 226,
    "flag1": false,
    "price": 0.21,
    "change": 0.015,
    "changePercent": 7.69,
    "high": 0.215,
    "low": 0.20,
    "volume": 3352152.0,
    "marketCapital": 701136.0,
    "oneYearChange": null
  },
  {
    "id": 5486,
    "date": 20170720,
    "stockId": 226,
    "flag1": false,
    "price": 0.195,
    "change": 0.005,
    "changePercent": 2.63,
    "high": 0.20,
    "low": 0.19,
    "volume": 2011030.0,
    "marketCapital": 392263.0,
    "oneYearChange": null
  },
  {
    "id": 5487,
    "date": 20170719,
    "stockId": 226,
    "flag1": false,
    "price": 0.19,
    "change": 0.01,
    "changePercent": 5.56,
    "high": 0.195,
    "low": 0.18,
    "volume": 2120227.0,
    "marketCapital": 398508.0,
    "oneYearChange": null
  },
  {
    "id": 5488,
    "date": 20170718,
    "stockId": 226,
    "flag1": false,
    "price": 0.18,
    "change": -0.01,
    "changePercent": -5.26,
    "high": 0.185,
    "low": 0.175,
    "volume": 2727461.0,
    "marketCapital": 491654.0,
    "oneYearChange": null
  },
  {
    "id": 5489,
    "date": 20170717,
    "stockId": 226,
    "flag1": false,
    "price": 0.19,
    "change": 0.005,
    "changePercent": 2.70,
    "high": 0.19,
    "low": 0.185,
    "volume": 1110068.0,
    "marketCapital": 209096.0,
    "oneYearChange": null
  }
]