[
  {
    "id": 3767,
    "date": 20170811,
    "stockId": 140,
    "flag1": false,
    "price": 1.895,
    "change": -0.08,
    "changePercent": -4.05,
    "high": 1.945,
    "low": 1.88,
    "volume": 2621272.0,
    "marketCapital": 4991141.0,
    "oneYearChange": null
  },
  {
    "id": 3768,
    "date": 20170810,
    "stockId": 140,
    "flag1": false,
    "price": 1.975,
    "change": 0.045,
    "changePercent": 2.33,
    "high": 1.985,
    "low": 1.95,
    "volume": 2168395.0,
    "marketCapital": 4269037.0,
    "oneYearChange": null
  },
  {
    "id": 3769,
    "date": 20170809,
    "stockId": 140,
    "flag1": false,
    "price": 1.93,
    "change": -0.045,
    "changePercent": -2.28,
    "high": 2.00,
    "low": 1.92,
    "volume": 2046852.0,
    "marketCapital": 3986598.0,
    "oneYearChange": null
  },
  {
    "id": 3770,
    "date": 20170808,
    "stockId": 140,
    "flag1": false,
    "price": 1.975,
    "change": -0.025,
    "changePercent": -1.25,
    "high": 2.05,
    "low": 1.965,
    "volume": 2379927.0,
    "marketCapital": 4744015.0,
    "oneYearChange": null
  },
  {
    "id": 3771,
    "date": 20170807,
    "stockId": 140,
    "flag1": false,
    "price": 2.00,
    "change": -0.03,
    "changePercent": -1.48,
    "high": 2.09,
    "low": 1.96,
    "volume": 3833785.0,
    "marketCapital": 7747870.0,
    "oneYearChange": null
  },
  {
    "id": 3772,
    "date": 20170804,
    "stockId": 140,
    "flag1": false,
    "price": 2.03,
    "change": 0.16,
    "changePercent": 8.56,
    "high": 2.03,
    "low": 1.88,
    "volume": 5561856.0,
    "marketCapital": 10946970.0,
    "oneYearChange": null
  },
  {
    "id": 3773,
    "date": 20170803,
    "stockId": 140,
    "flag1": false,
    "price": 1.87,
    "change": 0.035,
    "changePercent": 1.91,
    "high": 1.895,
    "low": 1.85,
    "volume": 2366294.0,
    "marketCapital": 4419726.0,
    "oneYearChange": null
  },
  {
    "id": 3774,
    "date": 20170802,
    "stockId": 140,
    "flag1": false,
    "price": 1.835,
    "change": -0.015,
    "changePercent": -0.81,
    "high": 1.90,
    "low": 1.835,
    "volume": 1793775.0,
    "marketCapital": 3336056.0,
    "oneYearChange": null
  },
  {
    "id": 3775,
    "date": 20170801,
    "stockId": 140,
    "flag1": false,
    "price": 1.85,
    "change": 0.01,
    "changePercent": 0.54,
    "high": 1.875,
    "low": 1.83,
    "volume": 2108045.0,
    "marketCapital": 3890995.0,
    "oneYearChange": null
  },
  {
    "id": 3776,
    "date": 20170731,
    "stockId": 140,
    "flag1": false,
    "price": 1.84,
    "change": 0.015,
    "changePercent": 0.82,
    "high": 1.885,
    "low": 1.835,
    "volume": 2109340.0,
    "marketCapital": 3916595.0,
    "oneYearChange": null
  },
  {
    "id": 3777,
    "date": 20170728,
    "stockId": 140,
    "flag1": false,
    "price": 1.825,
    "change": -0.05,
    "changePercent": -2.67,
    "high": 1.88,
    "low": 1.805,
    "volume": 3029302.0,
    "marketCapital": 5554002.0,
    "oneYearChange": null
  },
  {
    "id": 3778,
    "date": 20170727,
    "stockId": 140,
    "flag1": false,
    "price": 1.875,
    "change": -0.015,
    "changePercent": -0.79,
    "high": 1.925,
    "low": 1.87,
    "volume": 2407649.0,
    "marketCapital": 4569178.0,
    "oneYearChange": null
  },
  {
    "id": 3779,
    "date": 20170726,
    "stockId": 140,
    "flag1": false,
    "price": 1.89,
    "change": 0.07,
    "changePercent": 3.85,
    "high": 1.92,
    "low": 1.84,
    "volume": 2845851.0,
    "marketCapital": 5367975.0,
    "oneYearChange": null
  },
  {
    "id": 3780,
    "date": 20170725,
    "stockId": 140,
    "flag1": false,
    "price": 1.82,
    "change": 0.02,
    "changePercent": 1.11,
    "high": 1.84,
    "low": 1.80,
    "volume": 1707636.0,
    "marketCapital": 3112715.0,
    "oneYearChange": null
  },
  {
    "id": 3781,
    "date": 20170724,
    "stockId": 140,
    "flag1": false,
    "price": 1.80,
    "change": -0.125,
    "changePercent": -6.49,
    "high": 1.945,
    "low": 1.785,
    "volume": 4666734.0,
    "marketCapital": 8626330.0,
    "oneYearChange": null
  },
  {
    "id": 3782,
    "date": 20170721,
    "stockId": 140,
    "flag1": false,
    "price": 1.925,
    "change": 0.07,
    "changePercent": 3.77,
    "high": 1.94,
    "low": 1.835,
    "volume": 2443835.0,
    "marketCapital": 4652928.0,
    "oneYearChange": null
  },
  {
    "id": 3783,
    "date": 20170720,
    "stockId": 140,
    "flag1": false,
    "price": 1.855,
    "change": 0.015,
    "changePercent": 0.82,
    "high": 1.88,
    "low": 1.82,
    "volume": 2315974.0,
    "marketCapital": 4278192.0,
    "oneYearChange": null
  },
  {
    "id": 3784,
    "date": 20170719,
    "stockId": 140,
    "flag1": false,
    "price": 1.84,
    "change": 0.055,
    "changePercent": 3.08,
    "high": 1.875,
    "low": 1.725,
    "volume": 6213417.0,
    "marketCapital": 11259359.0,
    "oneYearChange": null
  },
  {
    "id": 3785,
    "date": 20170718,
    "stockId": 140,
    "flag1": false,
    "price": 1.785,
    "change": -0.06,
    "changePercent": -3.25,
    "high": 1.855,
    "low": 1.77,
    "volume": 4025273.0,
    "marketCapital": 7221174.0,
    "oneYearChange": null
  },
  {
    "id": 3786,
    "date": 20170717,
    "stockId": 140,
    "flag1": false,
    "price": 1.845,
    "change": -0.085,
    "changePercent": -4.40,
    "high": 1.98,
    "low": 1.83,
    "volume": 4344498.0,
    "marketCapital": 8175763.0,
    "oneYearChange": null
  }
]