[
  {
    "id": 7570,
    "date": 20170811,
    "stockId": 331,
    "flag1": false,
    "price": 0.76,
    "change": -0.015,
    "changePercent": -1.94,
    "high": 0.765,
    "low": 0.76,
    "volume": 39864.0,
    "marketCapital": 30317.0,
    "oneYearChange": null
  },
  {
    "id": 7571,
    "date": 20170810,
    "stockId": 331,
    "flag1": false,
    "price": 0.775,
    "change": 0.005,
    "changePercent": 0.65,
    "high": 0.775,
    "low": 0.77,
    "volume": 136773.0,
    "marketCapital": 105734.0,
    "oneYearChange": null
  },
  {
    "id": 7572,
    "date": 20170809,
    "stockId": 331,
    "flag1": false,
    "price": 0.77,
    "change": -0.01,
    "changePercent": -1.28,
    "high": 0.775,
    "low": 0.745,
    "volume": 91165.0,
    "marketCapital": 69449.0,
    "oneYearChange": null
  },
  {
    "id": 7573,
    "date": 20170808,
    "stockId": 331,
    "flag1": false,
    "price": 0.78,
    "change": -0.02,
    "changePercent": -2.50,
    "high": 0.78,
    "low": 0.76,
    "volume": 102168.0,
    "marketCapital": 79240.0,
    "oneYearChange": null
  },
  {
    "id": 7574,
    "date": 20170807,
    "stockId": 331,
    "flag1": false,
    "price": 0.80,
    "change": 0.025,
    "changePercent": 3.23,
    "high": 0.81,
    "low": 0.78,
    "volume": 198843.0,
    "marketCapital": 158181.0,
    "oneYearChange": null
  },
  {
    "id": 7575,
    "date": 20170804,
    "stockId": 331,
    "flag1": false,
    "price": 0.775,
    "change": 0.005,
    "changePercent": 0.65,
    "high": 0.78,
    "low": 0.765,
    "volume": 86265.0,
    "marketCapital": 66543.0,
    "oneYearChange": null
  },
  {
    "id": 7576,
    "date": 20170803,
    "stockId": 331,
    "flag1": false,
    "price": 0.77,
    "change": 0.00,
    "changePercent": 0.00,
    "high": 0.77,
    "low": 0.76,
    "volume": 52376.0,
    "marketCapital": 39827.0,
    "oneYearChange": null
  },
  {
    "id": 7577,
    "date": 20170802,
    "stockId": 331,
    "flag1": false,
    "price": 0.77,
    "change": -0.005,
    "changePercent": -0.65,
    "high": 0.77,
    "low": 0.745,
    "volume": 18413.0,
    "marketCapital": 13879.0,
    "oneYearChange": null
  },
  {
    "id": 7578,
    "date": 20170801,
    "stockId": 331,
    "flag1": false,
    "price": 0.775,
    "change": 0.005,
    "changePercent": 0.65,
    "high": 0.78,
    "low": 0.75,
    "volume": 413514.0,
    "marketCapital": 318090.0,
    "oneYearChange": null
  },
  {
    "id": 7579,
    "date": 20170731,
    "stockId": 331,
    "flag1": false,
    "price": 0.77,
    "change": -0.005,
    "changePercent": -0.65,
    "high": 0.77,
    "low": 0.745,
    "volume": 11386.0,
    "marketCapital": 8646.0,
    "oneYearChange": null
  },
  {
    "id": 7580,
    "date": 20170728,
    "stockId": 331,
    "flag1": false,
    "price": 0.775,
    "change": -0.005,
    "changePercent": -0.64,
    "high": 0.775,
    "low": 0.76,
    "volume": 30821.0,
    "marketCapital": 23604.0,
    "oneYearChange": null
  },
  {
    "id": 7581,
    "date": 20170727,
    "stockId": 331,
    "flag1": false,
    "price": 0.78,
    "change": -0.01,
    "changePercent": -1.27,
    "high": 0.78,
    "low": 0.77,
    "volume": 26725.0,
    "marketCapital": 20802.0,
    "oneYearChange": null
  },
  {
    "id": 7582,
    "date": 20170726,
    "stockId": 331,
    "flag1": false,
    "price": 0.79,
    "change": 0.015,
    "changePercent": 1.94,
    "high": 0.79,
    "low": 0.79,
    "volume": 13232.0,
    "marketCapital": 10453.0,
    "oneYearChange": null
  },
  {
    "id": 7583,
    "date": 20170725,
    "stockId": 331,
    "flag1": false,
    "price": 0.775,
    "change": 0.005,
    "changePercent": 0.65,
    "high": 0.79,
    "low": 0.775,
    "volume": 47661.0,
    "marketCapital": 37550.0,
    "oneYearChange": null
  },
  {
    "id": 7584,
    "date": 20170724,
    "stockId": 331,
    "flag1": false,
    "price": 0.77,
    "change": -0.01,
    "changePercent": -1.28,
    "high": 0.785,
    "low": 0.77,
    "volume": 112496.0,
    "marketCapital": 87752.0,
    "oneYearChange": null
  },
  {
    "id": 7585,
    "date": 20170721,
    "stockId": 331,
    "flag1": false,
    "price": 0.78,
    "change": 0.02,
    "changePercent": 2.63,
    "high": 0.78,
    "low": 0.765,
    "volume": 91177.0,
    "marketCapital": 70689.0,
    "oneYearChange": null
  },
  {
    "id": 7586,
    "date": 20170720,
    "stockId": 331,
    "flag1": false,
    "price": 0.76,
    "change": -0.035,
    "changePercent": -4.40,
    "high": 0.79,
    "low": 0.76,
    "volume": 235649.0,
    "marketCapital": 184994.0,
    "oneYearChange": null
  },
  {
    "id": 7587,
    "date": 20170719,
    "stockId": 331,
    "flag1": false,
    "price": 0.795,
    "change": 0.005,
    "changePercent": 0.63,
    "high": 0.795,
    "low": 0.78,
    "volume": 633042.0,
    "marketCapital": 499680.0,
    "oneYearChange": null
  },
  {
    "id": 7588,
    "date": 20170718,
    "stockId": 331,
    "flag1": false,
    "price": 0.79,
    "change": 0.03,
    "changePercent": 3.95,
    "high": 0.79,
    "low": 0.76,
    "volume": 766079.0,
    "marketCapital": 596173.0,
    "oneYearChange": null
  },
  {
    "id": 7589,
    "date": 20170717,
    "stockId": 331,
    "flag1": false,
    "price": 0.76,
    "change": 0.01,
    "changePercent": 1.33,
    "high": 0.765,
    "low": 0.75,
    "volume": 257933.0,
    "marketCapital": 196077.0,
    "oneYearChange": null
  }
]