[
  {
    "id": 9573,
    "date": 20170811,
    "stockId": 432,
    "flag1": false,
    "price": null,
    "change": null,
    "changePercent": null,
    "high": null,
    "low": null,
    "volume": 0.0,
    "marketCapital": 0.0,
    "oneYearChange": null
  },
  {
    "id": 9574,
    "date": 20170810,
    "stockId": 432,
    "flag1": false,
    "price": 2.41,
    "change": -0.04,
    "changePercent": -1.63,
    "high": 2.41,
    "low": 2.41,
    "volume": 4215.0,
    "marketCapital": 10158.0,
    "oneYearChange": null
  },
  {
    "id": 9575,
    "date": 20170809,
    "stockId": 432,
    "flag1": false,
    "price": 2.45,
    "change": 0.00,
    "changePercent": 0.00,
    "high": 2.45,
    "low": 2.45,
    "volume": 500.0,
    "marketCapital": 1225.0,
    "oneYearChange": null
  },
  {
    "id": 9576,
    "date": 20170808,
    "stockId": 432,
    "flag1": false,
    "price": null,
    "change": null,
    "changePercent": null,
    "high": null,
    "low": null,
    "volume": 0.0,
    "marketCapital": 0.0,
    "oneYearChange": null
  },
  {
    "id": 9577,
    "date": 20170807,
    "stockId": 432,
    "flag1": false,
    "price": 2.45,
    "change": 0.11,
    "changePercent": 4.70,
    "high": 2.45,
    "low": 2.43,
    "volume": 11340.0,
    "marketCapital": 27583.0,
    "oneYearChange": null
  },
  {
    "id": 9578,
    "date": 20170804,
    "stockId": 432,
    "flag1": false,
    "price": null,
    "change": null,
    "changePercent": null,
    "high": null,
    "low": null,
    "volume": 0.0,
    "marketCapital": 0.0,
    "oneYearChange": null
  },
  {
    "id": 9579,
    "date": 20170803,
    "stockId": 432,
    "flag1": false,
    "price": null,
    "change": null,
    "changePercent": null,
    "high": null,
    "low": null,
    "volume": 0.0,
    "marketCapital": 0.0,
    "oneYearChange": null
  },
  {
    "id": 9580,
    "date": 20170802,
    "stockId": 432,
    "flag1": false,
    "price": 2.34,
    "change": -0.02,
    "changePercent": -0.85,
    "high": 2.35,
    "low": 2.34,
    "volume": 10391.0,
    "marketCapital": 24319.0,
    "oneYearChange": null
  },
  {
    "id": 9581,
    "date": 20170801,
    "stockId": 432,
    "flag1": false,
    "price": null,
    "change": null,
    "changePercent": null,
    "high": null,
    "low": null,
    "volume": 0.0,
    "marketCapital": 0.0,
    "oneYearChange": null
  },
  {
    "id": 9582,
    "date": 20170731,
    "stockId": 432,
    "flag1": false,
    "price": 2.36,
    "change": -0.02,
    "changePercent": -0.84,
    "high": 2.38,
    "low": 2.36,
    "volume": 9395.0,
    "marketCapital": 22349.0,
    "oneYearChange": null
  },
  {
    "id": 9583,
    "date": 20170728,
    "stockId": 432,
    "flag1": false,
    "price": 2.38,
    "change": -0.11,
    "changePercent": -4.42,
    "high": 2.38,
    "low": 2.38,
    "volume": 3067.0,
    "marketCapital": 7299.0,
    "oneYearChange": null
  },
  {
    "id": 9584,
    "date": 20170727,
    "stockId": 432,
    "flag1": false,
    "price": 2.49,
    "change": -0.06,
    "changePercent": -2.35,
    "high": 2.50,
    "low": 2.49,
    "volume": 3145.0,
    "marketCapital": 7858.0,
    "oneYearChange": null
  },
  {
    "id": 9585,
    "date": 20170726,
    "stockId": 432,
    "flag1": false,
    "price": 2.55,
    "change": -0.10,
    "changePercent": -3.77,
    "high": 2.62,
    "low": 2.55,
    "volume": 8475.0,
    "marketCapital": 21673.0,
    "oneYearChange": null
  },
  {
    "id": 9586,
    "date": 20170725,
    "stockId": 432,
    "flag1": false,
    "price": 2.65,
    "change": 0.02,
    "changePercent": 0.76,
    "high": 2.65,
    "low": 2.59,
    "volume": 13790.0,
    "marketCapital": 36083.0,
    "oneYearChange": null
  },
  {
    "id": 9587,
    "date": 20170724,
    "stockId": 432,
    "flag1": false,
    "price": 2.63,
    "change": -0.07,
    "changePercent": -2.59,
    "high": 2.71,
    "low": 2.56,
    "volume": 14435.0,
    "marketCapital": 37774.0,
    "oneYearChange": null
  },
  {
    "id": 9588,
    "date": 20170721,
    "stockId": 432,
    "flag1": false,
    "price": 2.70,
    "change": 0.15,
    "changePercent": 5.88,
    "high": 2.75,
    "low": 2.55,
    "volume": 22186.0,
    "marketCapital": 59173.0,
    "oneYearChange": null
  },
  {
    "id": 9589,
    "date": 20170720,
    "stockId": 432,
    "flag1": false,
    "price": 2.55,
    "change": 0.21,
    "changePercent": 8.97,
    "high": 2.55,
    "low": 2.35,
    "volume": 59850.0,
    "marketCapital": 146308.0,
    "oneYearChange": null
  },
  {
    "id": 9590,
    "date": 20170719,
    "stockId": 432,
    "flag1": false,
    "price": null,
    "change": null,
    "changePercent": null,
    "high": null,
    "low": null,
    "volume": 0.0,
    "marketCapital": 0.0,
    "oneYearChange": null
  },
  {
    "id": 9591,
    "date": 20170718,
    "stockId": 432,
    "flag1": false,
    "price": null,
    "change": null,
    "changePercent": null,
    "high": null,
    "low": null,
    "volume": 0.0,
    "marketCapital": 0.0,
    "oneYearChange": null
  },
  {
    "id": 9592,
    "date": 20170717,
    "stockId": 432,
    "flag1": false,
    "price": null,
    "change": null,
    "changePercent": null,
    "high": null,
    "low": null,
    "volume": 0.0,
    "marketCapital": 0.0,
    "oneYearChange": null
  }
]